full_outer_join/__init__.py
full_outer_join/__init__.pyi
full_outer_join/join.py
full_outer_join/join.pyi
full_outer_join-1.0.0.dist-info/LICENSE
full_outer_join-1.0.0.dist-info/WHEEL
full_outer_join-1.0.0.dist-info/METADATA
full_outer_join-1.0.0.dist-info/RECORD
