Metadata-Version: 2.1
Name: full_outer_join
Version: 1.0.0
Summary: Lazy iterables for full outer join, inner join, and left and right join
Keywords: itertools,iterator,iteration,join
Author-email: David Gilman <davidgilman1@gmail.com>
Requires-Python: >=3.8
Classifier: Development Status :: 5 - Production/Stable
Classifier: Intended Audience :: Developers
Classifier: Natural Language :: English
Classifier: License :: OSI Approved :: MIT License
Classifier: Programming Language :: Python :: 3
Classifier: Programming Language :: Python :: 3 :: Only
Classifier: Topic :: Software Development :: Libraries
Project-URL: Homepage, https://github.com/dgilman/full_outer_join
